shellmate/__init__.py
shellmate/shellmate.py
ShellMate-1.0.7.dist-info/LICENSE
ShellMate-1.0.7.dist-info/METADATA
ShellMate-1.0.7.dist-info/WHEEL
ShellMate-1.0.7.dist-info/entry_points.txt
ShellMate-1.0.7.dist-info/top_level.txt
ShellMate-1.0.7.dist-info/RECORD
