Metadata-Version: 2.1
Name: ShellMate
Version: 1.0.7
Summary: ShellMate: A GPT-Powered CLI Tool for Explaining and Finding Shell Commands
Home-page: https://github.com/Mercurius13/ShellMate
Author: Siddhant
Author-email: siddhant@zodevelopers.com
Classifier: Programming Language :: Python :: 3
Classifier: License :: OSI Approved :: MIT License
Classifier: Operating System :: OS Independent
Requires-Python: >=3.6
License-File: LICENSE
Requires-Dist: openai
Requires-Dist: argparse
Requires-Dist: python-dotenv
